generator_names/__init__.py
generator_names/generator_names.py
generator_names/data_names/russia/female_firstnames.txt
generator_names/data_names/russia/lastnames.txt
generator_names/data_names/russia/male_firstnames.txt
generator_names/data_names/usa/female_firstnames.txt
generator_names/data_names/usa/lastnames.txt
generator_names/data_names/usa/male_firstnames.txt
generator_names-0.3.0.dist-info/LICENSE
generator_names-0.3.0.dist-info/METADATA
generator_names-0.3.0.dist-info/WHEEL
generator_names-0.3.0.dist-info/top_level.txt
generator_names-0.3.0.dist-info/RECORD
