Metadata-Version: 2.2
Name: generator-names
Version: 0.3.0
Summary: A module for generating random names in English and Russian.
Home-page: https://github.com/yourusername/generator-names
Author: Misha
Author-email: bobyyy239@gmail.com
License: MIT
Classifier: Programming Language :: Python :: 3
Classifier: License :: OSI Approved :: MIT License
Classifier: Operating System :: OS Independent
Requires-Python: >=3.6
License-File: LICENSE
Dynamic: author
Dynamic: author-email
Dynamic: classifier
Dynamic: description
Dynamic: description-content-type
Dynamic: home-page
Dynamic: license
Dynamic: requires-python
Dynamic: summary
